tokensaver/__init__.py
tokensaver/cli.py
tokensaver/core.py
tokensaver-0.1.1.dist-info/licenses/LICENSE
tokensaver-0.1.1.dist-info/METADATA
tokensaver-0.1.1.dist-info/WHEEL
tokensaver-0.1.1.dist-info/entry_points.txt
tokensaver-0.1.1.dist-info/top_level.txt
tokensaver-0.1.1.dist-info/RECORD
